mkdocs_bibtex/__init__.py
mkdocs_bibtex/citation.py
mkdocs_bibtex/config.py
mkdocs_bibtex/plugin.py
mkdocs_bibtex/registry.py
mkdocs_bibtex/utils.py
mkdocs_bibtex-4.4.0.dist-info/licenses/LICENSE
mkdocs_bibtex-4.4.0.dist-info/METADATA
mkdocs_bibtex-4.4.0.dist-info/WHEEL
mkdocs_bibtex-4.4.0.dist-info/entry_points.txt
mkdocs_bibtex-4.4.0.dist-info/top_level.txt
mkdocs_bibtex-4.4.0.dist-info/RECORD
