Metadata-Version: 2.4
Name: mkdocs-bibtex
Version: 4.4.0
Summary: An MkDocs plugin that enables managing citations with BibTex
Author-email: Shyam Dwaraknath <16827130+shyamd@users.noreply.github.com>
License: BSD-3-Clause-LBNL
Project-URL: Homepage, https://github.com/shyamd/mkdocs-bibtex/
Keywords: mkdocs,python,markdown,bibtex
Requires-Python: >=3.6
License-File: LICENSE
Requires-Dist: mkdocs>=1.2
Requires-Dist: pybtex>=0.22
Requires-Dist: pypandoc>=1.5
Requires-Dist: requests>=2.8.1
Requires-Dist: validators>=0.19.0
Requires-Dist: setuptools>=68.0.0
Requires-Dist: responses>=0.25.6
Dynamic: license-file
